bh20seqanalyzer/__init__.py
bh20seqanalyzer/main.py
bh20sequploader/SARS-CoV-2-reference.fasta
bh20sequploader/__init__.py
bh20sequploader/bh20seq-options.yml
bh20sequploader/bh20seq-schema.yml
bh20sequploader/bh20seq-shex.rdf
bh20sequploader/main.py
bh20sequploader/qc_fasta.py
bh20sequploader/qc_metadata.py
bh20sequploader/validation/formats
bh20simplewebuploader/__init__.py
bh20simplewebuploader/main.py
bh20_seq_uploader-1.0.20200703212028.dist-info/LICENSE
bh20_seq_uploader-1.0.20200703212028.dist-info/METADATA
bh20_seq_uploader-1.0.20200703212028.dist-info/WHEEL
bh20_seq_uploader-1.0.20200703212028.dist-info/entry_points.txt
bh20_seq_uploader-1.0.20200703212028.dist-info/top_level.txt
bh20_seq_uploader-1.0.20200703212028.dist-info/zip-safe
bh20_seq_uploader-1.0.20200703212028.dist-info/RECORD
