Metadata-Version: 2.1
Name: bh20-seq-uploader
Version: 1.0.20200703212028
Summary: Biohackathon sequence uploader
Home-page: UNKNOWN
Author: Peter Amstutz
Author-email: peter.amstutz@curii.com
License: Apache 2.0
Platform: UNKNOWN
Requires-Python: >=3.5, <4
Requires-Dist: arvados-python-client
Requires-Dist: schema-salad
Requires-Dist: python-magic
Requires-Dist: pyshex
Requires-Dist: py-dateutil
Provides-Extra: web
Requires-Dist: flask ; extra == 'web'
Requires-Dist: pyyaml ; extra == 'web'
